config/example_read_r.json
config/hello_world_classifier_predict.json
config/hello_world_classifier_predict.yml
config/hello_world_classifier_train.json
config/hello_world_classifier_train.yml
config/hello_world_cluster_eval.json
config/hello_world_cluster_eval.yml
config/hello_world_cluster_simple_train.json
config/hello_world_cluster_simple_train.yml
config/hello_world_cluster_train.json
config/hello_world_cluster_train.yml
config/hello_world_custom_nodes.json
config/hello_world_custom_nodes.yml
config/hello_world_read_write.json
config/hello_world_read_write.yml
config/hello_world_regression_train.json
config/hello_world_regression_train.yml
data/tennis.csv
data/unclustered.csv
primrose/__init__.py
primrose/dag_runner.py
primrose/data_object.py
primrose/node_factory.py
primrose/notification_utils.py
primrose/util.py
primrose/base/__init__.py
primrose/base/conditional_path_node.py
primrose/base/do_nothing_node.py
primrose/base/model.py
primrose/base/node.py
primrose/base/pipeline.py
primrose/base/postprocess.py
primrose/base/reader.py
primrose/base/search_engine.py
primrose/base/sql_reader.py
primrose/base/success.py
primrose/base/transformer.py
primrose/base/transformer_sequence.py
primrose/base/writer.py
primrose/cleanup/__init__.py
primrose/cleanup/logging_success.py
primrose/conditionalpath/__init__.py
primrose/conditionalpath/simple_switch.py
primrose/configuration/__init__.py
primrose/configuration/configuration.py
primrose/configuration/configuration_dag.py
primrose/configuration/util.py
primrose/dag/__init__.py
primrose/dag/config_layer_traverser.py
primrose/dag/dag_traverser.py
primrose/dag/depth_first_traverser.py
primrose/dag/traverser_factory.py
primrose/dataviz/__init__.py
primrose/dataviz/cluster_plotter.py
primrose/models/__init__.py
primrose/models/minimal_search_engine.py
primrose/models/sklearn_classifier_model.py
primrose/models/sklearn_cluster_model.py
primrose/models/sklearn_model.py
primrose/models/sklearn_regression_model.py
primrose-2.0.0.dist-info/LICENSE
primrose-2.0.0.dist-info/METADATA
primrose-2.0.0.dist-info/WHEEL
primrose-2.0.0.dist-info/entry_points.txt
primrose-2.0.0.dist-info/top_level.txt
primrose-2.0.0.dist-info/RECORD
