Metadata-Version: 2.1
Name: primrose
Version: 2.0.0
Summary: Primrose: a framework for simple, quick modeling deployments
Author-email: WW Data Science <datascience@ww.com>
Maintainer-email: Brian Graham <brian.graham@ww.com>, Calvin Woo <calvin.woo@ww.com>, Pierre Winter <pierre.winter@ww.com>, Rakesh Ramesh <rakesh.ramesh@ww.com>
License: Apache License
Project-URL: Homepage, https://github.com/ww-tech/primrose
Project-URL: Documentation, https://ww-tech.github.io/primrose/
Classifier: Programming Language :: Python :: 3.8
Classifier: Operating System :: OS Independent
Requires-Python: >=3.8
License-File: LICENSE
Requires-Dist: pandas (>=1.5.3)
Requires-Dist: click (>=8.1.3)
Requires-Dist: scikit-learn (>=1.2.2)
Requires-Dist: jstyleson (>=0.0.2)
Requires-Dist: networkx (>=3.0)
Requires-Dist: dill (>=0.3.6)
Requires-Dist: pyyaml (>=6.0)
Requires-Dist: google-cloud-storage (>=2.7.0)
Requires-Dist: matplotlib (>=3.7.1)
Requires-Dist: jinja2 (>=3.1.2)
Requires-Dist: boto3 (>=1.26.93)
Requires-Dist: mysql-connector-python (>=8.0.32)
Requires-Dist: slackclient (>=2.9.4)
Requires-Dist: testfixtures (>=7.1.0)
Requires-Dist: moto (>=4.1.4)
Requires-Dist: nltk (>=3.8.1)
Requires-Dist: pydot (>=1.4.2)
Provides-Extra: r
Requires-Dist: rpy2 (>=3.5.10) ; extra == 'r'
Provides-Extra: plotting
Requires-Dist: pygraphviz (>=1.10) ; extra == 'plotting'
Provides-Extra: postgres
Requires-Dist: psycopg2-binary (>=2.9.5) ; extra == 'postgres'
Provides-Extra: test
Requires-Dist: pytest (>=7.2.2) ; extra == 'test'
